nrc-adams-py/__init__.py
nrc_adams_py/__init__.py
nrc_adams_py/constants.py
nrc_adams_py/core.py
nrc_adams_py/tests/__init__.py
nrc_adams_py/tests/test_core.py
nrc_adams_py-0.0.3.dist-info/LICENSE
nrc_adams_py-0.0.3.dist-info/METADATA
nrc_adams_py-0.0.3.dist-info/WHEEL
nrc_adams_py-0.0.3.dist-info/top_level.txt
nrc_adams_py-0.0.3.dist-info/RECORD
