Metadata-Version: 2.1
Name: nrc-adams-py
Version: 0.0.3
Summary: Python Class connect to NRC ADAMS API
Home-page: https://github.com/bradfox2/nrc_adams_py
Author: Brad Fox
Author-email: bradley.fox@avfintellitech.com
License: UNKNOWN
Platform: UNKNOWN
Classifier: Programming Language :: Python :: 3
Classifier: Operating System :: OS Independent
